[
  {
    "word": "good",
    "count": 17,
    "guest_ids": [
      "andy-richter",
      "bill-burr",
      "tina-fey",
      "lisa-kudrow",
      "will-arnett",
      "rashida-jones",
      "matt-damon",
      "ray-romano",
      "dave-grohl-krist-novoselic-and-steve-albini",
      "joel-mchale",
      "mike-schur",
      "christina-ricci",
      "jason-bateman",
      "slash",
      "aubrey-plaza"
    ],
    "episode_ids": [
      "andy-richter",
      "bill-burr-returns-again",
      "tina-fey",
      "lisa-kudrow-returns",
      "lisa-kudrow-returns-again",
      "will-arnett-returns",
      "rashida-jones",
      "matt-damon",
      "ray-romano",
      "dave-grohl-krist-novoselic-and-in-utero-producer-steve-albini",
      "joel-mchale",
      "mike-schur",
      "christina-ricci",
      "jason-bateman",
      "slash",
      "aubrey-plaza"
    ]
  },
  {
    "word": "and",
    "count": 16,
    "guest_ids": [
      "jeff-goldblum",
      "nikki-glaser",
      "matthew-rhys",
      "seth-meyers",
      "dan-levy",
      "tom-holland-and-dominic-sandbrook-of-the-rest-is-history-podcast",
      "jeff-bridges",
      "dave-grohl-krist-novoselic-and-steve-albini",
      "kelly-clarkson",
      "billie-eilish-and-finneas",
      "angela-kinsey-and-jenna-fischer",
      "anthony-anderson",
      "thomas-middleditch-and-ben-schwartz",
      "david-byrne",
      "jane-lynch"
    ],
    "episode_ids": [
      "jeff-goldblum-returns",
      "jeff-goldblum-returns-re-release",
      "nikki-glaser-returns-again",
      "matthew-rhys-returns",
      "seth-meyers",
      "dan-levy",
      "tom-holland-and-dominic-sandbrook-of-the-rest-is-history-podcast",
      "jeff-bridges",
      "dave-grohl-krist-novoselic-and-in-utero-producer-steve-albini",
      "kelly-clarkson",
      "billie-eilish-and-finneas",
      "angela-kinsey-and-jenna-fischer",
      "anthony-anderson",
      "thomas-middleditch-and-ben-schwartz",
      "david-byrne",
      "jane-lynch"
    ]
  },
  {
    "word": "excited",
    "count": 16,
    "guest_ids": [
      "david-spade",
      "janelle-james",
      "chelsea-peretti",
      "tracee-ellis-ross",
      "nicole-byer",
      "adam-mckay",
      "maria-bamford",
      "rivers-cuomo",
      "seth-meyers",
      "dan-levy",
      "billie-eilish-and-finneas",
      "angela-kinsey-and-jenna-fischer",
      "b-j-novak",
      "goldie-hawn",
      "jimmy-kimmel",
      "rachel-dratch"
    ],
    "episode_ids": [
      "david-spade",
      "janelle-james",
      "chelsea-peretti",
      "tracee-ellis-ross",
      "nicole-byer",
      "adam-mckay",
      "maria-bamford",
      "rivers-cuomo",
      "seth-meyers",
      "dan-levy",
      "billie-eilish-and-finneas",
      "angela-kinsey-and-jenna-fischer",
      "b-j-novak",
      "goldie-hawn",
      "jimmy-kimmel",
      "rachel-dratch"
    ]
  },
  {
    "word": "optimistic",
    "count": 15,
    "guest_ids": [
      "jb-smoove",
      "elizabeth-banks",
      "w-kamau-bell",
      "michelle-obama",
      "paul-scheer",
      "ayo-edebiri",
      "ezra-koenig",
      "quinta-brunson",
      "paul-f-tompkins",
      "julie-bowen",
      "daniel-radcliffe",
      "rob-lowe",
      "steve-coogan",
      "john-oliver",
      "dax-shepard"
    ],
    "episode_ids": [
      "jb-smoove-returns",
      "elizabeth-banks",
      "w-kamau-bell",
      "michelle-obama",
      "paul-scheer-returns",
      "ayo-edebiri",
      "ezra-koenig",
      "quinta-brunson",
      "paul-f-tompkins",
      "julie-bowen",
      "daniel-radcliffe",
      "rob-lowe",
      "steve-coogan",
      "john-oliver",
      "dax-shepard"
    ]
  },
  {
    "word": "a",
    "count": 14,
    "guest_ids": [
      "tracee-ellis-ross",
      "julia-louis-dreyfus",
      "werner-herzog",
      "nate-bargatze",
      "johnny-knoxville",
      "denis-leary",
      "josh-safdie",
      "jeff-bridges",
      "ambassador-rahm-emanuel",
      "alan-yang",
      "joel-mchale",
      "hillary-and-chelsea-clinton",
      "tracy-morgan-live-at-the-beacon-theater",
      "desus-nice"
    ],
    "episode_ids": [
      "tracee-ellis-ross",
      "julia-louis-dreyfus",
      "werner-herzog",
      "nate-bargatze",
      "johnny-knoxville",
      "denis-leary",
      "josh-safdie",
      "jeff-bridges",
      "ambassador-rahm-emanuel",
      "alan-yang",
      "joel-mchale",
      "hillary-and-chelsea-clinton",
      "tracy-morgan-live-at-the-beacon-theater",
      "desus-mero"
    ]
  },
  {
    "word": "very",
    "count": 11,
    "guest_ids": [
      "darcy-carden",
      "judd-apatow",
      "michelle-obama",
      "jeff-bridges",
      "danny-mcbride",
      "jason-segel",
      "john-wilson",
      "ali-wong",
      "dax-shepard",
      "niecy-nash-betts"
    ],
    "episode_ids": [
      "darcy-carden-returns",
      "judd-apatow-returns",
      "michelle-obama-returns",
      "jeff-bridges",
      "danny-mcbride",
      "jason-segel",
      "john-wilson",
      "ali-wong",
      "dax-shepard",
      "niecy-nash-betts"
    ]
  },
  {
    "word": "honored",
    "count": 10,
    "guest_ids": [
      "jack-mcbrayer",
      "nikki-glaser",
      "will-forte",
      "cecily-strong",
      "kelly-clarkson",
      "sebastian-maniscalco",
      "jordan-peele",
      "jane-lynch",
      "zach-braff"
    ],
    "episode_ids": [
      "jack-mcbrayer",
      "nikki-glaser-returns-again",
      "will-forte",
      "cecily-strong",
      "kelly-clarkson",
      "sebastian-maniscalco",
      "jordan-peele",
      "jane-lynch",
      "zach-braff"
    ]
  },
  {
    "word": "confused",
    "count": 9,
    "guest_ids": [
      "bob-odenkirk",
      "matthew-rhys",
      "lizzy-caplan",
      "chris-robinson",
      "albert-brooks-and-rob-reiner",
      "harrison-ford",
      "hannah-einbinder",
      "keith-urban",
      "hannah-gadsby"
    ],
    "episode_ids": [
      "bob-odenkirk",
      "matthew-rhys-returns",
      "lizzy-caplan",
      "chris-robinson",
      "albert-brooks-and-rob-reiner",
      "harrison-ford",
      "hannah-einbinder",
      "keith-urban",
      "hannah-gadsby"
    ]
  },
  {
    "word": "great",
    "count": 8,
    "guest_ids": [
      "charles-barkley",
      "bill-hader",
      "w-kamau-bell",
      "kenan-thompson",
      "lin-manuel-miranda",
      "hillary-and-chelsea-clinton",
      "john-leguizamo",
      "chris-martin"
    ],
    "episode_ids": [
      "charles-barkley",
      "bill-hader",
      "w-kamau-bell",
      "kenan-thompson",
      "lin-manuel-miranda",
      "hillary-and-chelsea-clinton",
      "john-leguizamo",
      "chris-martin"
    ]
  },
  {
    "word": "really",
    "count": 8,
    "guest_ids": [
      "lisa-kudrow",
      "tracee-ellis-ross",
      "julia-louis-dreyfus",
      "billie-eilish-and-finneas",
      "diego-luna",
      "goldie-hawn",
      "chris-martin"
    ],
    "episode_ids": [
      "lisa-kudrow-returns",
      "lisa-kudrow-returns-again",
      "tracee-ellis-ross",
      "julia-louis-dreyfus",
      "billie-eilish-and-finneas",
      "diego-luna",
      "goldie-hawn",
      "chris-martin"
    ]
  }
]